ScalaFunctional-0.6.0.dist-info/DESCRIPTION.rst
ScalaFunctional-0.6.0.dist-info/METADATA
ScalaFunctional-0.6.0.dist-info/RECORD
ScalaFunctional-0.6.0.dist-info/WHEEL
ScalaFunctional-0.6.0.dist-info/metadata.json
ScalaFunctional-0.6.0.dist-info/top_level.txt
functional/__init__.py
functional/lineage.py
functional/pipeline.py
functional/streams.py
functional/transformations.py
functional/util.py
functional/test/__init__.py
functional/test/test_functional.py
functional/test/test_streams.py
functional/test/test_util.py
