Metadata-Version: 2.0
Name: ScalaFunctional
Version: 0.6.0
Summary: Package for creating data pipelines, LINQ, and chain functional programming
Home-page: https://github.com/EntilZha/ScalaFunctional
Author: Pedro Rodriguez
Author-email: ski.rodriguez@gmail.com
License: MIT
Keywords: functional LINQ pipeline data collection rdd scala
Platform: UNKNOWN
Classifier: Development Status :: 4 - Beta
Classifier: Intended Audience :: Developers
Classifier: License :: OSI Approved :: MIT License
Classifier: Programming Language :: Python :: 2.7
Classifier: Programming Language :: Python :: 3.3
Classifier: Programming Language :: Python :: 3.4
Classifier: Programming Language :: Python :: 3.5
Classifier: Programming Language :: Python :: Implementation :: CPython
Classifier: Programming Language :: Python :: Implementation :: PyPy
Classifier: Natural Language :: English
Classifier: Operating System :: OS Independent
Classifier: Topic :: Software Development :: Libraries :: Python Modules
Requires-Dist: future
Requires-Dist: six
